{
  "current_page": 1,
  "current_page_items": 6,
  "number_of_pages": 1,
  "number_of_items": 6,
  "products": [
    {
      "code": "6937",
      "action_currently_yn": false,
      "code_supplier": null,
      "supplier": null,
      "ean": null,
      "product_id": 34,
      "active_yn": true,
      "archived_yn": false,
      "replacement_product_code": null,
      "can_add_to_basket_yn": true,
      "adult_yn": false,
      "set_yn": false,
      "in_set_yn": false,
      "exclude_from_search_yn": false,
      "descriptions": [
        {
          "language": "cs",
          "title": "Zichovec 11\u00b0 Irish Black Stout",
          "short_description": "Pro fanou\u0161ky lehk\u00fdch pra\u017een\u00fdch piv dle vzor\u016f z Irska si na leto\u0161n\u00ed zimu v Zichovci p\u0159ipravili sv\u016fj prvn\u00ed Irish Dry Stout. Vysok\u00e1 pitelnost, kr\u00e9mov\u00e9 t\u011blo a dominantn\u00ed chu\u0165 pra\u017een\u00fdch k\u00e1vov\u00fdch slad\u016f budou skv\u011bl\u00fdmi partnery pro podzimn\u00ed ve\u010dery. Stout je va\u0159en\u00fd specificky zpracovan\u00e9ho je\u010dmene, kter\u00fd se hrav\u011b postaral o \u017e\u00e1douc\u00ed elegatn\u011b k\u00e1vov\u00fd profil.",
          "long_description": "<p><strong>Slo\u017een\u00ed:<\/strong><br>voda,\u00a0<ins>je\u010dn\u00fd\u00a0slad<\/ins>,\u00a0<ins>je\u010dn\u00e9 vlo\u010dky<\/ins>, chmelov\u00e9 produkty<\/p>\r\n<p><strong>O pivovaru:<\/strong><br>Zichoveck\u00fd pivovar za\u010d\u00ednal v obci Zichovec mezi Louny a Slan\u00fdm, kter\u00e1 m\u00e1 podle Googlu jenom 93 obyvatel. Vzhledem ke kvalit\u011b sv\u00fdch piv ale dok\u00e1zal p\u0159it\u00e1hnout z\u00e1kazn\u00edky z cel\u00e9ho okol\u00ed. Nyn\u00ed pivovar Zichovec va\u0159\u00ed pivo v nov\u00e9m modern\u00edm are\u00e1lu na okraji Loun. Pivovar je vybaven\u00fd nejmodern\u011bj\u0161\u00ed technologi\u00ed a jeho kapacitu vyu\u017e\u00edv\u00e1 i cel\u00e1 \u0159ada \u010desk\u00fdch ko\u010dovn\u00fdch pivovar\u016f. Jejich nepopul\u00e1rn\u011bj\u0161\u00edm pivem je Magor a ze speci\u00e1l\u016f doporu\u010dujeme ochutnat (a vyp\u00edt) skv\u011ble odlad\u011bnou a nachmelenou\u00a0Double IPU.<\/p>",
          "url": "https:\/\/www.beer-shop.cz\/p\/zichovec-11-irish-black-stout",
          "seo_title": null,
          "seo_description": null,
          "seo_url": "zichovec-11-irish-black-stout",
          "unit": "ks"
        },
        {
          "language": "sk",
          "title": "Zichovec 11\u00b0 Irish Black Stout",
          "short_description": "Pre fan\u00fa\u0161ikov \u013eahk\u00fdch pra\u017een\u00fdch p\u00edv pod\u013ea vzorov z \u00cdrska si na tohtoro\u010dn\u00fa zimu v Zichovci pripravili svoj prv\u00fd Irish Dry Stout. Vysok\u00e1 pite\u013enos\u0165, kr\u00e9mov\u00e9 telo a dominantn\u00e1 chu\u0165 pra\u017een\u00fdch k\u00e1vov\u00fdch sladov bud\u00fa skvel\u00fdmi partnermi na jesenn\u00e9 ve\u010dery. Stout je varen\u00fd \u0161pecificky spracovan\u00e9ho ja\u010dme\u0148a, ktor\u00fd sa hravo postaral o \u017eiaduci elegatne k\u00e1vov\u00fd profil.",
          "long_description": "<p><strong>Zlo\u017eenie:<\/strong><br>voda, ja\u010dmenn\u00fd slad, ja\u010dmenn\u00e9 vlo\u010dky, chme\u013eov\u00e9 produkty<\/p>\r\n<p><strong>O pivovare:<\/strong><br>Zichoveck\u00fd pivovar za\u010d\u00ednal v obci Zichovec medzi Louny a Slan\u00fdm, ktor\u00e1 m\u00e1 pod\u013ea Googlu iba 93 obyvate\u013eov. Vzh\u013eadom ku kvalite svojich p\u00edv ale dok\u00e1zal pritiahnu\u0165 z\u00e1kazn\u00edkov z cel\u00e9ho okolia. Teraz pivovar Zichovec var\u00ed pivo v novom modernom are\u00e1li na okraji Loun. Pivovar je vybaven\u00fd najmodernej\u0161ou technol\u00f3giou a jeho kapacitu vyu\u017e\u00edva aj cel\u00fd rad \u010desk\u00fdch ko\u010dovn\u00fdch pivovarov. Ich najpopul\u00e1rnej\u0161\u00edm pivom je Magor a zo \u0161peci\u00e1lov odpor\u00fa\u010dame ochutna\u0165 (a vypi\u0165) skvele odladen\u00fa a nachmelen\u00fa Double IPU.<\/p>",
          "url": "http:\/\/sk.beer-shop.cz\/p\/zichovec-11-irish-black-stout",
          "seo_title": null,
          "seo_description": null,
          "seo_url": null,
          "unit": "ks"
        },
        {
          "language": "en",
          "title": "Zichovec 11\u00b0 Irish Black Stout",
          "short_description": null,
          "long_description": null,
          "url": "http:\/\/eu.beer-shop.cz\/p\/zichovec-11-irish-black-stout",
          "seo_title": null,
          "seo_description": null,
          "seo_url": null,
          "unit": "ks"
        }
      ],
      "manufacturer": "Zichovec",
      "stock": 4,
      "stock_position": null,
      "availability": "Skladem 3-5 ks",
      "availability_type": "InStock",
      "weight": 500,
      "shipment_group": null,
      "images": [
        {
          "url": "https:\/\/beershop.s24.cdn-upgates.com\/i\/i65dca34383e9d-img-4050-2.jpg",
          "main_yn": true,
          "list_yn": true,
          "position": 1,
          "titles": []
        }
      ],
      "categories": [
        {
          "category_id": 111,
          "code": "K00002",
          "main_yn": true,
          "position": 6,
          "name": "\u010cesko"
        },
        {
          "category_id": 113,
          "code": "K00004",
          "main_yn": false,
          "position": 6,
          "name": "Plechovky p\u016fllitry"
        },
        {
          "category_id": 110,
          "code": "K00001",
          "main_yn": false,
          "position": 6,
          "name": "PIVO PODLE ZEM\u00cd"
        },
        {
          "category_id": 112,
          "code": "K00003",
          "main_yn": false,
          "position": 5,
          "name": "PIVO PODLE OBJEMU"
        },
        {
          "category_id": 115,
          "code": "K00006",
          "main_yn": false,
          "position": 5,
          "name": "PIVO PODLE STYLU"
        },
        {
          "category_id": 156,
          "code": "K00047",
          "main_yn": false,
          "position": 4,
          "name": "KATALOG PIV"
        },
        {
          "category_id": 117,
          "code": "K00008",
          "main_yn": false,
          "position": 1,
          "name": "Stouty & Portery"
        }
      ],
      "groups": [],
      "prices": [
        {
          "currency": "CZK",
          "language": "cs",
          "pricelists": [
            {
              "name": "V\u00fdchoz\u00ed",
              "price_original": 89,
              "product_discount": null,
              "product_discount_real": 0,
              "price_sale": null,
              "price_with_vat": 89,
              "price_without_vat": 73.55
            }
          ],
          "price_purchase": null,
          "price_common": 0,
          "vat": 21,
          "recycling_fee": null
        },
        {
          "currency": "EUR",
          "language": "en",
          "pricelists": [
            {
              "name": "V\u00fdchoz\u00ed",
              "price_original": 2253.48,
              "product_discount": null,
              "product_discount_real": 0,
              "price_sale": null,
              "price_with_vat": 2253.48,
              "price_without_vat": 2253.48
            }
          ],
          "price_purchase": null,
          "price_common": 0,
          "vat": 0,
          "recycling_fee": null
        },
        {
          "currency": "EUR",
          "language": "sk",
          "pricelists": [
            {
              "name": "V\u00fdchoz\u00ed",
              "price_original": 2253.48,
              "product_discount": null,
              "product_discount_real": 0,
              "price_sale": null,
              "price_with_vat": 2253.48,
              "price_without_vat": 2253.48
            }
          ],
          "price_purchase": null,
          "price_common": 0,
          "vat": 0,
          "recycling_fee": null
        }
      ],
      "variants": [],
      "metas": [
        {
          "key": "categorytext_zbozi_cz",
          "type": "select",
          "value": ""
        },
        {
          "key": "col",
          "type": "input",
          "value": ""
        },
        {
          "key": "cont",
          "type": "input",
          "value": ""
        },
        {
          "key": "custom_zaloha",
          "type": "number",
          "value": "0"
        },
        {
          "key": "productname_zbozi_cz",
          "type": "input",
          "value": ""
        },
        {
          "key": "product_zbozi_cz",
          "type": "input",
          "value": ""
        },
        {
          "key": "redirect_301",
          "type": "textarea",
          "values": {
            "cs": {
              "language": "cs",
              "value": ""
            },
            "en": {
              "language": "en",
              "value": ""
            },
            "sk": {
              "language": "sk",
              "value": "\/sk\/"
            }
          }
        }
      ],
      "creation_time": "2024-02-26T13:22:07+01:00",
      "last_update_time": "2024-03-06T16:05:48+01:00",
      "admin_url": "https:\/\/beershop.admin.s24.upgates.com\/manager\/products\/main\/default\/34"
    },
    {
      "code": "2307",
      "action_currently_yn": false,
      "code_supplier": null,
      "supplier": null,
      "ean": null,
      "product_id": 35,
      "active_yn": true,
      "archived_yn": false,
      "replacement_product_code": null,
      "can_add_to_basket_yn": true,
      "adult_yn": false,
      "set_yn": false,
      "in_set_yn": false,
      "exclude_from_search_yn": false,
      "descriptions": [
        {
          "language": "cs",
          "title": "Chroust 12\u00b0 Jura Le\u017e\u00e1k",
          "short_description": "Vylad\u011bn\u00fd le\u017e\u00e1\u010dek od Chrousta va\u0159en\u00fd na 2 rmuty z plze\u0148sk\u00e9ho a mnichovsk\u00e9ho sladu a chmelen\u00fd \u017eateck\u00fdm chmelem z \u00da\u0161t\u011bcka. M\u00e1 st\u0159edn\u00ed a\u017e vy\u0161\u0161\u00ed ho\u0159kost a pln\u00e9 t\u011blo. Jeho pitelnost je opravdu vysok\u00e1.",
          "long_description": "<p><strong>Slo\u017een\u00ed:<\/strong><br>voda,\u00a0<ins>je\u010dn\u00fd slad<\/ins>, chmelov\u00e9 produkty<\/p>\r\n<p><strong>O pivovaru:<br>\u200b<\/strong>Chroust je stylov\u00fd ko\u010dovn\u00fd pivovar, za kter\u00fdm stoj\u00ed Karol\u00edna a Jirka Chroustov\u0161t\u00ed. Pivo bez filtrace a pasterizace va\u0159\u00ed v \u010desk\u00fdch \u0159emesln\u00fdch pivovarech ji\u017e od roku 2016. Hned od po\u010d\u00e1tku si nasadili la\u0165ku hodn\u011b vysoko a produkuj\u00ed pivn\u00ed speci\u00e1ly netradi\u010dn\u00edch chut\u00ed. V sou\u010dasnosti maj\u00ed vlastn\u00ed tanky um\u00edst\u011bn\u00e9 v pivovaru clock, kde produkuj\u00ed svoje ejly a le\u017e\u00e1ky. Pivo va\u0159\u00ed origin\u00e1ln\u011b, v t\u00e9 nejvy\u0161\u0161\u00ed kvalit\u011b a hlavn\u011b bez kompromis\u016f. A\u0165 u\u017e se pou\u0161t\u00ed do popul\u00e1rn\u00edch New England IPA nebo klasick\u00e9ho le\u017e\u00e1ku, cht\u011bj\u00ed aby bylo pivo harmonick\u00e9, chutn\u00e9 a aby v\u00e1s bavilo. D\u00edky skv\u011bl\u00e9 technologick\u00e9 vybavenosti, kterou Clock zast\u0159e\u0161uje, m\u016f\u017eou st\u00e1\u010det pivo do plechovek i lahv\u00ed v t\u00e9 nejlep\u0161\u00ed kondici.<\/p>",
          "url": "https:\/\/www.beer-shop.cz\/p\/chroust-12-jura-lezak",
          "seo_title": null,
          "seo_description": null,
          "seo_url": "chroust-12-jura-lezak",
          "unit": "ks"
        },
        {
          "language": "sk",
          "title": "Chroust 12\u00b0 Jura Le\u017eiak",
          "short_description": "Vyladen\u00fd le\u017eia\u010dik od Chr\u00fasta varen\u00fd na 2 rmuty z plzensk\u00e9ho a mn\u00edchovsk\u00e9ho sladu a chmelen\u00fd \u017eateck\u00fdm chme\u013eom z \u00da\u0161t\u011bcka. M\u00e1 stredn\u00fa a\u017e vy\u0161\u0161iu horkos\u0165 a pln\u00e9 telo. Jeho pite\u013enos\u0165 je skuto\u010dne vysok\u00e1.",
          "long_description": "<p><strong>Zlo\u017eenie:<\/strong><br>voda, ja\u010dmenn\u00fd slad, chme\u013eov\u00e9 produkty<\/p>\r\n<p><strong>O pivovare:<\/strong><br>Chroust je \u0161t\u00fdlov\u00fd ko\u010dovn\u00fd pivovar, za ktor\u00fdm stoj\u00ed Karol\u00edna a Jirka Chroustovsk\u00ed. Pivo bez filtr\u00e1cie a pasteriz\u00e1cie var\u00ed v \u010desk\u00fdch remeseln\u00fdch pivovaroch u\u017e od roku 2016. Hne\u010f od za\u010diatku si nasadili latku ve\u013emi vysoko a produkuj\u00fa pivn\u00e9 \u0161peci\u00e1ly netradi\u010dn\u00fdch chut\u00ed. V s\u00fa\u010dasnosti maj\u00fa vlastn\u00e9 tanky umiestnen\u00e9 v pivovare clock, kde produkuj\u00fa svoje ejly a le\u017eiaky. Pivo var\u00ed origin\u00e1lne, v tej najvy\u0161\u0161ej kvalite a hlavne bez kompromisov. \u010ci u\u017e sa p\u00fa\u0161\u0165a do popul\u00e1rnych New England IPA alebo klasick\u00e9ho le\u017eiaka, chc\u00fa aby bolo pivo harmonick\u00e9, chutn\u00e9 a aby v\u00e1s bavilo. V\u010faka skvelej technologickej vybavenosti, ktor\u00fa Clock zastre\u0161uje, m\u00f4\u017eu st\u00e1\u010da\u0165 pivo do plechoviek aj flia\u0161 v tej najlep\u0161ej kond\u00edcii.<\/p>",
          "url": "http:\/\/sk.beer-shop.cz\/p\/chroust-12-jura-leziak",
          "seo_title": null,
          "seo_description": null,
          "seo_url": "chroust-12-jura-leziak",
          "unit": "ks"
        },
        {
          "language": "en",
          "title": "Chroust 12\u00b0 Jura Lager",
          "short_description": null,
          "long_description": null,
          "url": "http:\/\/eu.beer-shop.cz\/p\/chroust-12-jura-lager",
          "seo_title": null,
          "seo_description": null,
          "seo_url": null,
          "unit": "ks"
        }
      ],
      "manufacturer": "Chroust",
      "stock": 1,
      "stock_position": null,
      "availability": "Skladem 1-2 ks",
      "availability_type": "InStock",
      "weight": 500,
      "shipment_group": null,
      "images": [
        {
          "url": "https:\/\/beershop.s24.cdn-upgates.com\/c\/c65ddccca2f52d-img-1970-2.jpg",
          "main_yn": true,
          "list_yn": true,
          "position": 1,
          "titles": []
        }
      ],
      "categories": [
        {
          "category_id": 111,
          "code": "K00002",
          "main_yn": true,
          "position": 5,
          "name": "\u010cesko"
        },
        {
          "category_id": 113,
          "code": "K00004",
          "main_yn": false,
          "position": 5,
          "name": "Plechovky p\u016fllitry"
        },
        {
          "category_id": 121,
          "code": "K00012",
          "main_yn": false,
          "position": 1,
          "name": "Le\u017e\u00e1ky"
        },
        {
          "category_id": 156,
          "code": "K00047",
          "main_yn": false,
          "position": 7,
          "name": "KATALOG PIV"
        },
        {
          "category_id": 110,
          "code": "K00001",
          "main_yn": false,
          "position": 7,
          "name": "PIVO PODLE ZEM\u00cd"
        },
        {
          "category_id": 112,
          "code": "K00003",
          "main_yn": false,
          "position": 6,
          "name": "PIVO PODLE OBJEMU"
        },
        {
          "category_id": 115,
          "code": "K00006",
          "main_yn": false,
          "position": 6,
          "name": "PIVO PODLE STYLU"
        }
      ],
      "groups": [],
      "prices": [
        {
          "currency": "CZK",
          "language": "cs",
          "pricelists": [
            {
              "name": "V\u00fdchoz\u00ed",
              "price_original": 79,
              "product_discount": null,
              "product_discount_real": 0,
              "price_sale": null,
              "price_with_vat": 79,
              "price_without_vat": 65.29
            }
          ],
          "price_purchase": null,
          "price_common": 0,
          "vat": 21,
          "recycling_fee": null
        },
        {
          "currency": "EUR",
          "language": "en",
          "pricelists": [
            {
              "name": "V\u00fdchoz\u00ed",
              "price_original": 2000.28,
              "product_discount": null,
              "product_discount_real": 0,
              "price_sale": null,
              "price_with_vat": 2000.28,
              "price_without_vat": 2000.28
            }
          ],
          "price_purchase": null,
          "price_common": 0,
          "vat": 0,
          "recycling_fee": null
        },
        {
          "currency": "EUR",
          "language": "sk",
          "pricelists": [
            {
              "name": "V\u00fdchoz\u00ed",
              "price_original": 2000.28,
              "product_discount": null,
              "product_discount_real": 0,
              "price_sale": null,
              "price_with_vat": 2000.28,
              "price_without_vat": 2000.28
            }
          ],
          "price_purchase": null,
          "price_common": 0,
          "vat": 0,
          "recycling_fee": null
        }
      ],
      "variants": [],
      "metas": [
        {
          "key": "categorytext_zbozi_cz",
          "type": "select",
          "value": ""
        },
        {
          "key": "col",
          "type": "input",
          "value": ""
        },
        {
          "key": "cont",
          "type": "input",
          "value": ""
        },
        {
          "key": "custom_zaloha",
          "type": "number",
          "value": "0"
        },
        {
          "key": "productname_zbozi_cz",
          "type": "input",
          "value": ""
        },
        {
          "key": "product_zbozi_cz",
          "type": "input",
          "value": ""
        },
        {
          "key": "redirect_301",
          "type": "textarea",
          "values": {
            "cs": {
              "language": "cs",
              "value": ""
            },
            "en": {
              "language": "en",
              "value": ""
            },
            "sk": {
              "language": "sk",
              "value": "\/sk\/"
            }
          }
        }
      ],
      "creation_time": "2024-02-27T12:47:40+01:00",
      "last_update_time": "2024-03-06T15:01:36+01:00",
      "admin_url": "https:\/\/beershop.admin.s24.upgates.com\/manager\/products\/main\/default\/35"
    },
    {
      "code": "2862",
      "action_currently_yn": false,
      "code_supplier": null,
      "supplier": null,
      "ean": null,
      "product_id": 36,
      "active_yn": true,
      "archived_yn": false,
      "replacement_product_code": null,
      "can_add_to_basket_yn": true,
      "adult_yn": false,
      "set_yn": false,
      "in_set_yn": false,
      "exclude_from_search_yn": false,
      "descriptions": [
        {
          "language": "cs",
          "title": "Permon 11\u00b0 P\u0161eni\u010dn\u00e9",
          "short_description": "Svrchn\u011b kva\u0161en\u00e9 p\u0161eni\u010dn\u00e9 pivo od Permonu. M\u00e1 sv\u011btlou a\u017e sl\u00e1movou barvou s vysokou nasycenost\u00ed a bohatou p\u011bnou. Chutn\u00e1 p\u0159esn\u011b jak m\u00e1 \u010desk\u00e1 p\u0161enice chutnat, tak\u017ee sladov\u00e1, obiln\u00e1, ko\u0159en\u011bn\u00e1 a lehce ovocn\u00e1 chu\u0165. Pivo m\u00e1 st\u0159edn\u00ed a\u017e lehce vy\u0161\u0161\u00ed \u0159\u00edz a st\u0159edn\u00ed plnost t\u011bla. Je samoz\u0159ejm\u011b nefiltrovan\u00e9 a nepasterovan\u00e9.",
          "long_description": "<p><strong>Slo\u017een\u00ed:<\/strong><br>voda,\u00a0<ins>p\u0161eni\u010dn\u00fd slad<\/ins>, chmelov\u00e9 produkty, pivovarsk\u00e9 kvasinky<\/p>\r\n<p><strong>O pivovaru:<\/strong><br>V\u00fdroba piva Permon byla zah\u00e1jena v roce 2006. Zakladatelem a majitelem je pan Ladislav\u00a0S\u00e1s a spole\u010dne se sv\u00fdm synem Michalem postupn\u011b vybudovali jeden z nejv\u00fdznamn\u011bj\u0161\u00edch minipivovar\u016f v \u010cesku.\u00a0V roce 2011 byl pivovar modernizov\u00e1n a bylo mu m\u011bstem Sokolov ud\u011bleno pr\u00e1vo v\u00e1re\u010dn\u00e9. Pivovar je te\u010f vybaven\u00fd\u00a0automatickou\u00a0st\u00e1\u010dec\u00ed linkou\u00a0na sklen\u011bn\u00e9 lahve, co\u017e mu umo\u017e\u0148uje udr\u017eovat \u0161irok\u00fd sortiment pivn\u00edch speci\u00e1l\u016f s rozumnou trvanlivost\u00ed. Pivovar craft beer\u00a0vyv\u00e1\u017e\u00ed i do zahrani\u010d\u00ed a jejich piva m\u016f\u017eete\u00a0ochutnat\u00a0na v\u011bt\u0161in\u011b na\u0161ich pivn\u00edch festival\u016f. Ob\u010das zpest\u0159\u00ed jejich nab\u00eddku spolupr\u00e1ce s n\u011bkter\u00fdm ko\u010dovn\u00fdm pivovarem.<\/p>",
          "url": "https:\/\/www.beer-shop.cz\/p\/permon-11-psenicne",
          "seo_title": null,
          "seo_description": null,
          "seo_url": "permon-11-psenicne",
          "unit": "ks"
        },
        {
          "language": "sk",
          "title": "Permon 11\u00b0 P\u0161eni\u010dn\u00e9",
          "short_description": "Sladov\u00e1, obiln\u00e1, korenist\u00e1 a \u013eahko ovocn\u00e1 chu\u0165. Pivo m\u00e1 stredn\u00e9 a\u017e mierne vy\u0161\u0161ie nas\u00fdtenie a stredn\u00e9 plnos\u0165 tela. Je samozrejme nefiltrovan\u00e9 a nepasterizovan\u00e9. Pivo je bez farb\u00edv sladidiel a chemick\u00fdch pr\u00edsad. Vyroben\u00e9 klasickou technol\u00f3giou s otvoren\u00fdm kvasen\u00edm. Ide teda o tradi\u010dn\u00e9 pr\u00edrodne riadne kvasen\u00e9 nepasterizovan\u00e9 \u017eiv\u00e9 pivo bez pr\u00edsad.",
          "long_description": "<p><strong>Zlo\u017eenie:<\/strong><br>voda, p\u0161eni\u010dn\u00fd slad, chme\u013eov\u00e9 produkty, pivovarsk\u00e9 kvasinky<\/p>\r\n<p><strong>O pivovare:<\/strong><br>V\u00fdroba piva Permon bola zah\u00e1jen\u00e1 v roku 2006. Zakladate\u013eom a majite\u013eom je p\u00e1n Ladislav S\u00e1s a spolo\u010dne so svojim synom Michalom postupne vybudovali jeden z najv\u00fdznamnej\u0161\u00edch minipivovarov v \u010cesku. V roku 2011 bol pivovar modernizovan\u00fd a bolo mu mestom Sokolov udelen\u00e9 pr\u00e1vo v\u00e1re\u010dn\u00e9. Pivovar je teraz vybaven\u00fd automatickou st\u00e1\u010dacou linkou na sklenen\u00e9 f\u013ea\u0161e, \u010do mu umo\u017e\u0148uje udr\u017eova\u0165 \u0161irok\u00fd sortiment pivn\u00fdch \u0161peci\u00e1lov s rozumnou trvanlivos\u0165ou. Pivovar craft beer vyv\u00e1\u017ea aj do zahrani\u010dia a ich piv\u00e1 m\u00f4\u017eete ochutna\u0165 na v\u00e4\u010d\u0161ine na\u0161ich pivn\u00fdch festivalov. Ob\u010das spestr\u00ed ich ponuku spolupr\u00e1ce s niektor\u00fdm ko\u010dovn\u00fdm pivovarom.<\/p>",
          "url": "http:\/\/sk.beer-shop.cz\/p\/permon-11-psenicne",
          "seo_title": null,
          "seo_description": null,
          "seo_url": "permon-11-psenicne",
          "unit": "ks"
        }
      ],
      "manufacturer": "Permon",
      "stock": 0,
      "stock_position": null,
      "availability": "Te\u010f vyprod\u00e1no",
      "availability_type": "NotAvailable",
      "weight": 900,
      "shipment_group": null,
      "images": [
        {
          "url": "https:\/\/beershop.s24.cdn-upgates.com\/l\/l65ddced358dd3-img-2035.jpg",
          "main_yn": true,
          "list_yn": true,
          "position": 1,
          "titles": []
        }
      ],
      "categories": [
        {
          "category_id": 111,
          "code": "K00002",
          "main_yn": true,
          "position": 4,
          "name": "\u010cesko"
        },
        {
          "category_id": 122,
          "code": "K00013",
          "main_yn": false,
          "position": 1,
          "name": "P\u0161eni\u010dn\u00e1 (+ \u017eitn\u00e1)"
        },
        {
          "category_id": 130,
          "code": "K00021",
          "main_yn": false,
          "position": 1,
          "name": "Lahve p\u016fllitry"
        },
        {
          "category_id": 156,
          "code": "K00047",
          "main_yn": false,
          "position": 6,
          "name": "KATALOG PIV"
        },
        {
          "category_id": 110,
          "code": "K00001",
          "main_yn": false,
          "position": 8,
          "name": "PIVO PODLE ZEM\u00cd"
        },
        {
          "category_id": 112,
          "code": "K00003",
          "main_yn": false,
          "position": 7,
          "name": "PIVO PODLE OBJEMU"
        },
        {
          "category_id": 115,
          "code": "K00006",
          "main_yn": false,
          "position": 7,
          "name": "PIVO PODLE STYLU"
        }
      ],
      "groups": [],
      "prices": [
        {
          "currency": "CZK",
          "language": "cs",
          "pricelists": [
            {
              "name": "V\u00fdchoz\u00ed",
              "price_original": 65,
              "product_discount": null,
              "product_discount_real": 0,
              "price_sale": null,
              "price_with_vat": 65,
              "price_without_vat": 53.72
            }
          ],
          "price_purchase": null,
          "price_common": 0,
          "vat": 21,
          "recycling_fee": 3
        },
        {
          "currency": "EUR",
          "language": "sk",
          "pricelists": [
            {
              "name": "V\u00fdchoz\u00ed",
              "price_original": 1645.8,
              "product_discount": null,
              "product_discount_real": 0,
              "price_sale": null,
              "price_with_vat": 1645.8,
              "price_without_vat": 1645.8
            }
          ],
          "price_purchase": null,
          "price_common": 0,
          "vat": 0,
          "recycling_fee": 0.15
        }
      ],
      "variants": [],
      "metas": [
        {
          "key": "categorytext_zbozi_cz",
          "type": "select",
          "value": ""
        },
        {
          "key": "col",
          "type": "input",
          "value": ""
        },
        {
          "key": "cont",
          "type": "input",
          "value": ""
        },
        {
          "key": "custom_zaloha",
          "type": "number",
          "value": "3"
        },
        {
          "key": "productname_zbozi_cz",
          "type": "input",
          "value": ""
        },
        {
          "key": "product_zbozi_cz",
          "type": "input",
          "value": ""
        },
        {
          "key": "redirect_301",
          "type": "textarea",
          "values": {
            "cs": {
              "language": "cs",
              "value": ""
            },
            "en": {
              "language": "en",
              "value": ""
            },
            "sk": {
              "language": "sk",
              "value": "\/sk\/"
            }
          }
        }
      ],
      "creation_time": "2024-02-27T12:56:13+01:00",
      "last_update_time": "2024-03-06T14:41:04+01:00",
      "admin_url": "https:\/\/beershop.admin.s24.upgates.com\/manager\/products\/main\/default\/36"
    },
    {
      "code": "3264",
      "action_currently_yn": false,
      "code_supplier": null,
      "supplier": null,
      "ean": null,
      "product_id": 37,
      "active_yn": true,
      "archived_yn": false,
      "replacement_product_code": null,
      "can_add_to_basket_yn": true,
      "adult_yn": false,
      "set_yn": false,
      "in_set_yn": false,
      "exclude_from_search_yn": false,
      "descriptions": [
        {
          "language": "cs",
          "title": "Matu\u0161ka 12\u00b0 California",
          "short_description": "\u0158emesln\u00e9 pivo typu American Pale Ale s p\u0159\u00edhodn\u00fdm n\u00e1zvem California. Skv\u011bl\u00e1 chu\u0165 v pod\u00e1n\u00ed Adama Matu\u0161ky. V\u00fdborn\u011b piteln\u00e9, vyv\u00e1\u017een\u00e9 a p\u0159\u00edjemn\u011b chmelen\u00e9 pivo.",
          "long_description": "<p><strong>Slo\u017een\u00ed:<\/strong><br>voda,\u00a0<ins>je\u010dn\u00fd slad<\/ins>, chmelov\u00e9 produkty<\/p>\r\n<p><strong>O pivovaru:<\/strong><br>Pivovar zalo\u017eil sl\u00e1dek Martin Matu\u0161ka, kter\u00fd v\u00a0pivovarnick\u00e9m oboru pracuje od roku 1981. Pivovar Matu\u0161ka se nach\u00e1z\u00ed v\u00a0obci Broumy, kter\u00e1 le\u017e\u00ed v\u00a0Chr\u00e1n\u011bn\u00e9 krajinn\u00e9 oblasti K\u0159ivokl\u00e1tsko. Pivo Matu\u0161ka vyr\u00e1b\u00ed \u0159emeslnou cestou bez filtrace a pasterizace. Pivo si d\u00edky tomu uchov\u00e1v\u00e1 vlastnosti \u010derstv\u00e9ho piva to\u010den\u00e9ho p\u0159\u00edmo z pivn\u00edho sklepa. P\u0159i va\u0159en\u00ed z\u00e1sadn\u011b nepou\u017e\u00edvaj\u00ed cukr, sirupy ani chmelov\u00fd extrakt a pivo va\u0159\u00ed\u00a0dekok\u010dn\u00edm rmutovac\u00edm zp\u016fsobem, kter\u00fd d\u00e1v\u00e1 pln\u011bj\u0161\u00ed chlebnat\u00e1 piva.<\/p>",
          "url": "https:\/\/www.beer-shop.cz\/p\/matuska-12-california",
          "seo_title": null,
          "seo_description": null,
          "seo_url": "matuska-12-california",
          "unit": "ks"
        },
        {
          "language": "sk",
          "title": "Matu\u0161ka 12\u00b0 California",
          "short_description": "Pivo v \u0161t\u00fdle American Pale Ale je in\u0161pirovan\u00e9 Kaliforniou. Pivovar Matu\u0161ka sa sna\u017e\u00ed do ka\u017edej v\u00e1rky svojho piva California v\u0161tiepi\u0165 kusok optimizmu, slobody a slnka. Jedn\u00e1 sa o ve\u013emi pite\u013en\u00fa dvan\u00e1stku s jemnou nas\u00fdtenos\u0165ou a vy\u0161\u0161ou plnos\u0165ou. Chu\u0165 je ovocn\u00e1 a hork\u00e1 so sladov\u00fdm doznievan\u00edm. Chmele Citra a Cascade.",
          "long_description": "<p><strong>Zlo\u017eenie:<\/strong><br>voda, ja\u010dmenn\u00fd slad, chme\u013eov\u00e9 produkty<\/p>\r\n<p><strong>O pivovare:<\/strong><br>Pivovar zalo\u017eil sl\u00e1dok Martin Matu\u0161ka, ktor\u00fd v pivovarn\u00edckom odbore pracuje od roku 1981. Pivovar Matu\u0161ka sa nach\u00e1dza v obci Broumy, ktor\u00e1 le\u017e\u00ed v Chr\u00e1nenej krajinnej oblasti K\u0159ivokl\u00e1tsko. Pivo Matu\u0161ka vyr\u00e1ba remeseln\u00fa cestou bez filtr\u00e1cie a pasteriz\u00e1cie. Pivo si v\u010faka tomu uchov\u00e1va vlastnosti \u010derstv\u00e9ho piva to\u010den\u00e9ho priamo z pivnej pivnice. Pri varen\u00ed z\u00e1sadne nepou\u017e\u00edvaj\u00fa cukor, sirupy ani chme\u013eov\u00fd extrakt a pivo var\u00ed dekok\u010dn\u00fdm rmutovac\u00edm sp\u00f4sobom, ktor\u00fd d\u00e1va pln\u0161ie chlebnat\u00e9 piv\u00e1.<\/p>",
          "url": "http:\/\/sk.beer-shop.cz\/p\/matuska-12-california",
          "seo_title": null,
          "seo_description": null,
          "seo_url": "matuska-12-california",
          "unit": "ks"
        }
      ],
      "manufacturer": "Matu\u0161ka",
      "stock": 10,
      "stock_position": null,
      "availability": "Skladem > 10 ks",
      "availability_type": "InStock",
      "weight": 1450,
      "shipment_group": null,
      "images": [
        {
          "url": "https:\/\/beershop.s24.cdn-upgates.com\/f\/f65ddcfb388755-img-3429.jpg",
          "main_yn": true,
          "list_yn": true,
          "position": 1,
          "titles": []
        }
      ],
      "categories": [
        {
          "category_id": 111,
          "code": "K00002",
          "main_yn": true,
          "position": 3,
          "name": "\u010cesko"
        },
        {
          "category_id": 114,
          "code": "K00005",
          "main_yn": false,
          "position": 1,
          "name": "Lahve sedmi\u010dky"
        },
        {
          "category_id": 116,
          "code": "K00007",
          "main_yn": false,
          "position": 4,
          "name": "Pale Ale (IPA, APA, NEIPA)"
        },
        {
          "category_id": 156,
          "code": "K00047",
          "main_yn": false,
          "position": 5,
          "name": "KATALOG PIV"
        },
        {
          "category_id": 110,
          "code": "K00001",
          "main_yn": false,
          "position": 4,
          "name": "PIVO PODLE ZEM\u00cd"
        },
        {
          "category_id": 112,
          "code": "K00003",
          "main_yn": false,
          "position": 8,
          "name": "PIVO PODLE OBJEMU"
        },
        {
          "category_id": 115,
          "code": "K00006",
          "main_yn": false,
          "position": 8,
          "name": "PIVO PODLE STYLU"
        }
      ],
      "groups": [],
      "prices": [
        {
          "currency": "CZK",
          "language": "cs",
          "pricelists": [
            {
              "name": "V\u00fdchoz\u00ed",
              "price_original": 149,
              "product_discount": null,
              "product_discount_real": 0,
              "price_sale": null,
              "price_with_vat": 149,
              "price_without_vat": 123.14
            }
          ],
          "price_purchase": null,
          "price_common": 0,
          "vat": 21,
          "recycling_fee": null
        },
        {
          "currency": "EUR",
          "language": "sk",
          "pricelists": [
            {
              "name": "V\u00fdchoz\u00ed",
              "price_original": 3772.68,
              "product_discount": null,
              "product_discount_real": 0,
              "price_sale": null,
              "price_with_vat": 3772.68,
              "price_without_vat": 3772.68
            }
          ],
          "price_purchase": null,
          "price_common": 0,
          "vat": 0,
          "recycling_fee": null
        }
      ],
      "variants": [],
      "metas": [
        {
          "key": "categorytext_zbozi_cz",
          "type": "select",
          "value": ""
        },
        {
          "key": "col",
          "type": "input",
          "value": ""
        },
        {
          "key": "cont",
          "type": "input",
          "value": ""
        },
        {
          "key": "custom_zaloha",
          "type": "number",
          "value": "0"
        },
        {
          "key": "productname_zbozi_cz",
          "type": "input",
          "value": ""
        },
        {
          "key": "product_zbozi_cz",
          "type": "input",
          "value": ""
        },
        {
          "key": "redirect_301",
          "type": "textarea",
          "values": {
            "cs": {
              "language": "cs",
              "value": ""
            },
            "en": {
              "language": "en",
              "value": ""
            },
            "sk": {
              "language": "sk",
              "value": "\/sk\/"
            }
          }
        }
      ],
      "creation_time": "2024-02-27T13:01:37+01:00",
      "last_update_time": "2024-03-06T15:11:47+01:00",
      "admin_url": "https:\/\/beershop.admin.s24.upgates.com\/manager\/products\/main\/default\/37"
    },
    {
      "code": "1206",
      "action_currently_yn": false,
      "code_supplier": null,
      "supplier": null,
      "ean": null,
      "product_id": 39,
      "active_yn": true,
      "archived_yn": false,
      "replacement_product_code": null,
      "can_add_to_basket_yn": true,
      "adult_yn": false,
      "set_yn": false,
      "in_set_yn": false,
      "exclude_from_search_yn": false,
      "descriptions": [
        {
          "language": "cs",
          "title": "Brewdog 15\u00b0 Silk Road Mango Lychee NEIPA",
          "short_description": "Silk Road dal\u0161\u00ed plechovka od Brewdogu ve stylu New England IPA. Jde o siln\u00fd hazy ejl s bohatou v\u016fn\u00ed manga, li\u010di a citrus\u016f. P\u0159id\u00e1n\u00ed p\u0161enice ke slad\u016fm vykouzlilo pln\u011bj\u0161\u00ed chu\u0165, kter\u00e1 skv\u011ble dopl\u0148uje \u017eiv\u00e9 tropick\u00e9 t\u00f3ny.",
          "long_description": "<p><strong>Slo\u017een\u00ed:<\/strong><br>voda,\u00a0<ins>je\u010dn\u00fd slad<\/ins>,\u00a0<ins>torrifikovan\u00e1 p\u0161enice<\/ins>,<span>\u00a0<\/span><ins>ovesn\u00fd slad<\/ins>, chmel, p\u0159\u00edrodn\u00ed mangov\u00e9 aroma, p\u0159\u00edrodn\u00ed li\u010di aroma<\/p>\r\n<p><strong>O pivovaru:<\/strong><br>Martina a Jamese\u00a0nudily pr\u016fmyslov\u011b va\u0159en\u00e9\u00a0le\u017e\u00e1ky a nezaj\u00edmav\u00e9\u00a0ejly, kter\u00e9 se\u00a0prod\u00e1valy\u00a0v Brit\u00e1nii,\u00a0a tak se to rozhodli vy\u0159e\u0161it. Z t\u00e9to my\u0161lenky\u00a0se v dubnu 2007 narodil BrewDog. Bylo jim teprve 24 let, kdy\u017e si pronajali\u00a0budovu v Fraserburghu a za\u010dali d\u011blat hardcore dom\u00e1c\u00ed piva. Postupn\u011b se popularita jejich piva zvy\u0161ovala a\u017e na sou\u010dasnou hv\u011bzdnou \u00farove\u0148. Do\u0161lo k \u00fapisu akci\u00ed pivovaru\u00a0a postupn\u00e9mu otev\u00edr\u00e1n\u00ed Brewdog bar\u016f po cel\u00e9m sv\u011bt\u011b. V roce 2015 uva\u0159ili celkem 65 druh\u016f piva a dod\u00e1vaj\u00ed je do v\u00edce ne\u017e 60 zem\u00ed. Na na\u0161em eshopu je samoz\u0159ejm\u011b\u00a0nem\u016f\u017eeme vynechat, proto\u017ee je mus\u00ed vyzkou\u0161et ka\u017ed\u00fd \u010dlen craft beer komunity.<\/p>",
          "url": "https:\/\/www.beer-shop.cz\/p\/brewdog-15-silk-road-mango-lychee-neipa",
          "seo_title": null,
          "seo_description": null,
          "seo_url": "brewdog-15-silk-road-mango-lychee-neipa",
          "unit": "ks"
        },
        {
          "language": "sk",
          "title": "Brewdog 15\u00b0 Silk Road Mango Lychee NEIPA",
          "short_description": "Silk Road dal\u0161\u00ed plechovka od Brewdogu ve stylu New England IPA. Jde o siln\u00fd hazy ejl s bohatou v\u016fn\u00ed manga, li\u010di a citrus\u016f. P\u0159id\u00e1n\u00ed p\u0161enice ke slad\u016fm vykouzlilo pln\u011bj\u0161\u00ed chu\u0165, kter\u00e1 skv\u011ble dopl\u0148uje \u017eiv\u00e9 tropick\u00e9 t\u00f3ny.",
          "long_description": "<p><strong>Slo\u017een\u00ed:<\/strong><br>voda,\u00a0<ins>je\u010dn\u00fd slad<\/ins>,\u00a0<ins>torrifikovan\u00e1 p\u0161enice<\/ins>,<span>\u00a0<\/span><ins>ovesn\u00fd slad<\/ins>, chmel, p\u0159\u00edrodn\u00ed mangov\u00e9 aroma, p\u0159\u00edrodn\u00ed li\u010di aroma<\/p>\r\n<p><strong>O pivovaru:<\/strong><br>Martina a Jamese\u00a0nudily pr\u016fmyslov\u011b va\u0159en\u00e9\u00a0le\u017e\u00e1ky a nezaj\u00edmav\u00e9\u00a0ejly, kter\u00e9 se\u00a0prod\u00e1valy\u00a0v Brit\u00e1nii,\u00a0a tak se to rozhodli vy\u0159e\u0161it. Z t\u00e9to my\u0161lenky\u00a0se v dubnu 2007 narodil BrewDog. Bylo jim teprve 24 let, kdy\u017e si pronajali\u00a0budovu v Fraserburghu a za\u010dali d\u011blat hardcore dom\u00e1c\u00ed piva. Postupn\u011b se popularita jejich piva zvy\u0161ovala a\u017e na sou\u010dasnou hv\u011bzdnou \u00farove\u0148. Do\u0161lo k \u00fapisu akci\u00ed pivovaru\u00a0a postupn\u00e9mu otev\u00edr\u00e1n\u00ed Brewdog bar\u016f po cel\u00e9m sv\u011bt\u011b. V roce 2015 uva\u0159ili celkem 65 druh\u016f piva a dod\u00e1vaj\u00ed je do v\u00edce ne\u017e 60 zem\u00ed. Na na\u0161em eshopu je samoz\u0159ejm\u011b\u00a0nem\u016f\u017eeme vynechat, proto\u017ee je mus\u00ed vyzkou\u0161et ka\u017ed\u00fd \u010dlen craft beer komunity.<\/p>",
          "url": "http:\/\/sk.beer-shop.cz\/p\/brewdog-15-silk-road-mango-lychee-neipa",
          "seo_title": null,
          "seo_description": null,
          "seo_url": "brewdog-15-silk-road-mango-lychee-neipa",
          "unit": "ks"
        },
        {
          "language": "en",
          "title": "Brewdog 15\u00b0 Silk Road Mango Lychee NEIPA",
          "short_description": "Silk Road dal\u0161\u00ed plechovka od Brewdogu ve stylu New England IPA. Jde o siln\u00fd hazy ejl s bohatou v\u016fn\u00ed manga, li\u010di a citrus\u016f. P\u0159id\u00e1n\u00ed p\u0161enice ke slad\u016fm vykouzlilo pln\u011bj\u0161\u00ed chu\u0165, kter\u00e1 skv\u011ble dopl\u0148uje \u017eiv\u00e9 tropick\u00e9 t\u00f3ny.",
          "long_description": "<p><strong>Slo\u017een\u00ed:<\/strong><br>voda,\u00a0<ins>je\u010dn\u00fd slad<\/ins>,\u00a0<ins>torrifikovan\u00e1 p\u0161enice<\/ins>,<span>\u00a0<\/span><ins>ovesn\u00fd slad<\/ins>, chmel, p\u0159\u00edrodn\u00ed mangov\u00e9 aroma, p\u0159\u00edrodn\u00ed li\u010di aroma<\/p>\r\n<p><strong>O pivovaru:<\/strong><br>Martina a Jamese\u00a0nudily pr\u016fmyslov\u011b va\u0159en\u00e9\u00a0le\u017e\u00e1ky a nezaj\u00edmav\u00e9\u00a0ejly, kter\u00e9 se\u00a0prod\u00e1valy\u00a0v Brit\u00e1nii,\u00a0a tak se to rozhodli vy\u0159e\u0161it. Z t\u00e9to my\u0161lenky\u00a0se v dubnu 2007 narodil BrewDog. Bylo jim teprve 24 let, kdy\u017e si pronajali\u00a0budovu v Fraserburghu a za\u010dali d\u011blat hardcore dom\u00e1c\u00ed piva. Postupn\u011b se popularita jejich piva zvy\u0161ovala a\u017e na sou\u010dasnou hv\u011bzdnou \u00farove\u0148. Do\u0161lo k \u00fapisu akci\u00ed pivovaru\u00a0a postupn\u00e9mu otev\u00edr\u00e1n\u00ed Brewdog bar\u016f po cel\u00e9m sv\u011bt\u011b. V roce 2015 uva\u0159ili celkem 65 druh\u016f piva a dod\u00e1vaj\u00ed je do v\u00edce ne\u017e 60 zem\u00ed. Na na\u0161em eshopu je samoz\u0159ejm\u011b\u00a0nem\u016f\u017eeme vynechat, proto\u017ee je mus\u00ed vyzkou\u0161et ka\u017ed\u00fd \u010dlen craft beer komunity.<\/p>",
          "url": "http:\/\/eu.beer-shop.cz\/p\/brewdog-15-silk-road-mango-lychee-neipa",
          "seo_title": null,
          "seo_description": null,
          "seo_url": "brewdog-15-silk-road-mango-lychee-neipa",
          "unit": "ks"
        }
      ],
      "manufacturer": "Brewdog",
      "stock": null,
      "stock_position": null,
      "availability": "Skladem > 10 ks",
      "availability_type": "InStock",
      "weight": 500,
      "shipment_group": null,
      "images": [
        {
          "url": "https:\/\/beershop.s24.cdn-upgates.com\/7\/765e8836973812-img-4306-2.jpg",
          "main_yn": true,
          "list_yn": true,
          "position": 1,
          "titles": []
        }
      ],
      "categories": [
        {
          "category_id": 110,
          "code": "K00001",
          "main_yn": false,
          "position": 3,
          "name": "PIVO PODLE ZEM\u00cd"
        },
        {
          "category_id": 112,
          "code": "K00003",
          "main_yn": false,
          "position": 3,
          "name": "PIVO PODLE OBJEMU"
        },
        {
          "category_id": 113,
          "code": "K00004",
          "main_yn": false,
          "position": 3,
          "name": "Plechovky p\u016fllitry"
        },
        {
          "category_id": 115,
          "code": "K00006",
          "main_yn": false,
          "position": 3,
          "name": "PIVO PODLE STYLU"
        },
        {
          "category_id": 116,
          "code": "K00007",
          "main_yn": true,
          "position": 2,
          "name": "Pale Ale (IPA, APA, NEIPA)"
        },
        {
          "category_id": 156,
          "code": "K00047",
          "main_yn": false,
          "position": 3,
          "name": "KATALOG PIV"
        },
        {
          "category_id": 161,
          "code": "K00052",
          "main_yn": false,
          "position": 1,
          "name": "Anglie"
        }
      ],
      "groups": [],
      "prices": [
        {
          "currency": "CZK",
          "language": "cs",
          "pricelists": [
            {
              "name": "V\u00fdchoz\u00ed",
              "price_original": 109,
              "product_discount": null,
              "product_discount_real": 0,
              "price_sale": null,
              "price_with_vat": 109,
              "price_without_vat": 90.08
            }
          ],
          "price_purchase": null,
          "price_common": 0,
          "vat": 21,
          "recycling_fee": null
        },
        {
          "currency": "EUR",
          "language": "en",
          "pricelists": [
            {
              "name": "V\u00fdchoz\u00ed",
              "price_original": 2759.88,
              "product_discount": null,
              "product_discount_real": 0,
              "price_sale": null,
              "price_with_vat": 2759.88,
              "price_without_vat": 2759.88
            }
          ],
          "price_purchase": null,
          "price_common": 0,
          "vat": 0,
          "recycling_fee": null
        },
        {
          "currency": "EUR",
          "language": "sk",
          "pricelists": [
            {
              "name": "V\u00fdchoz\u00ed",
              "price_original": 2759.88,
              "product_discount": null,
              "product_discount_real": 0,
              "price_sale": null,
              "price_with_vat": 2759.88,
              "price_without_vat": 2759.88
            }
          ],
          "price_purchase": null,
          "price_common": 0,
          "vat": 0,
          "recycling_fee": null
        }
      ],
      "variants": [],
      "metas": [
        {
          "key": "categorytext_zbozi_cz",
          "type": "select",
          "value": ""
        },
        {
          "key": "col",
          "type": "input",
          "value": ""
        },
        {
          "key": "cont",
          "type": "input",
          "value": ""
        },
        {
          "key": "custom_zaloha",
          "type": "number",
          "value": "0"
        },
        {
          "key": "productname_zbozi_cz",
          "type": "input",
          "value": ""
        },
        {
          "key": "product_zbozi_cz",
          "type": "input",
          "value": ""
        },
        {
          "key": "redirect_301",
          "type": "textarea",
          "values": {
            "cs": {
              "language": "cs",
              "value": ""
            },
            "en": {
              "language": "en",
              "value": ""
            },
            "sk": {
              "language": "sk",
              "value": "\/sk\/"
            }
          }
        }
      ],
      "creation_time": "2024-03-06T15:41:01+01:00",
      "last_update_time": "2024-03-06T16:01:04+01:00",
      "admin_url": "https:\/\/beershop.admin.s24.upgates.com\/manager\/products\/main\/default\/39"
    },
    {
      "code": "1001",
      "action_currently_yn": false,
      "code_supplier": null,
      "supplier": null,
      "ean": "7622210496225",
      "product_id": 41,
      "active_yn": false,
      "archived_yn": false,
      "replacement_product_code": null,
      "can_add_to_basket_yn": true,
      "adult_yn": false,
      "set_yn": false,
      "in_set_yn": false,
      "exclude_from_search_yn": false,
      "descriptions": [
        {
          "language": "cs",
          "title": "Zlaty Dalmatyn 101",
          "short_description": "Pro fanou\u0161ky lehk\u00fdch pra\u017een\u00fdch piv dle vzor\u016f z Irska si na leto\u0161n\u00ed zimu v Zichovci p\u0159ipravili sv\u016fj prvn\u00ed Irish Dry Stout. Vysok\u00e1 pitelnost, kr\u00e9mov\u00e9 t\u011blo a dominantn\u00ed chu\u0165 pra\u017een\u00fdch k\u00e1vov\u00fdch slad\u016f budou skv\u011bl\u00fdmi partnery pro podzimn\u00ed ve\u010dery. Stout je va\u0159en\u00fd specificky zpracovan\u00e9ho je\u010dmene, kter\u00fd se hrav\u011b postaral o \u017e\u00e1douc\u00ed elegatn\u011b k\u00e1vov\u00fd profil.",
          "long_description": "<p><strong>Slo\u017een\u00ed:<\/strong><br>voda,\u00a0<ins>je\u010dn\u00fd\u00a0slad<\/ins>,\u00a0<ins>je\u010dn\u00e9 vlo\u010dky<\/ins>, chmelov\u00e9 produkty<\/p>\r\n    <p><strong>O pivovaru:<\/strong><br>Zichoveck\u00fd pivovar za\u010d\u00ednal v obci Zichovec mezi Louny a Slan\u00fdm, kter\u00e1 m\u00e1 podle Googlu jenom 93 obyvatel. Vzhledem ke kvalit\u011b sv\u00fdch piv ale dok\u00e1zal p\u0159it\u00e1hnout z\u00e1kazn\u00edky z cel\u00e9ho okol\u00ed. Nyn\u00ed pivovar Zichovec va\u0159\u00ed pivo v nov\u00e9m modern\u00edm are\u00e1lu na okraji Loun. Pivovar je vybaven\u00fd nejmodern\u011bj\u0161\u00ed technologi\u00ed a jeho kapacitu vyu\u017e\u00edv\u00e1 i cel\u00e1 \u0159ada \u010desk\u00fdch ko\u010dovn\u00fdch pivovar\u016f. Jejich nepopul\u00e1rn\u011bj\u0161\u00edm pivem je Magor a ze speci\u00e1l\u016f doporu\u010dujeme ochutnat (a vyp\u00edt) skv\u011ble odlad\u011bnou a nachmelenou\u00a0Double IPU.<\/p>",
          "url": "https:\/\/www.beer-shop.cz\/p\/zlaty-dalmatyn-101",
          "seo_title": null,
          "seo_description": null,
          "seo_url": "zlaty-dalmatyn-101",
          "unit": "ks"
        },
        {
          "language": "en",
          "title": "Zlaty Dalmatyn 101",
          "short_description": null,
          "long_description": null,
          "url": "http:\/\/eu.beer-shop.cz\/p\/zlaty-dalmatyn-101",
          "seo_title": null,
          "seo_description": null,
          "seo_url": "zlaty-dalmatyn-101",
          "unit": "ks"
        },
        {
          "language": "sk",
          "title": "Zlaty Dalmatyn 101",
          "short_description": "Pre fan\u00fa\u0161ikov \u013eahk\u00fdch pra\u017een\u00fdch p\u00edv pod\u013ea vzorov z \u00cdrska si na tohtoro\u010dn\u00fa zimu v Zichovci pripravili svoj prv\u00fd Irish Dry Stout. Vysok\u00e1 pite\u013enos\u0165, kr\u00e9mov\u00e9 telo a dominantn\u00e1 chu\u0165 pra\u017een\u00fdch k\u00e1vov\u00fdch sladov bud\u00fa skvel\u00fdmi partnermi na jesenn\u00e9 ve\u010dery. Stout je varen\u00fd \u0161pecificky spracovan\u00e9ho ja\u010dme\u0148a, ktor\u00fd sa hravo postaral o \u017eiaduci elegatne k\u00e1vov\u00fd profil.",
          "long_description": "<p><strong>Zlo\u017eenie:<\/strong><br>voda, ja\u010dmenn\u00fd slad, ja\u010dmenn\u00e9 vlo\u010dky, chme\u013eov\u00e9 produkty<\/p>\r\n    <p><strong>O pivovare:<\/strong><br>Zichoveck\u00fd pivovar za\u010d\u00ednal v obci Zichovec medzi Louny a Slan\u00fdm, ktor\u00e1 m\u00e1 pod\u013ea Googlu iba 93 obyvate\u013eov. Vzh\u013eadom ku kvalite svojich p\u00edv ale dok\u00e1zal pritiahnu\u0165 z\u00e1kazn\u00edkov z cel\u00e9ho okolia. Teraz pivovar Zichovec var\u00ed pivo v novom modernom are\u00e1li na okraji Loun. Pivovar je vybaven\u00fd najmodernej\u0161ou technol\u00f3giou a jeho kapacitu vyu\u017e\u00edva aj cel\u00fd rad \u010desk\u00fdch ko\u010dovn\u00fdch pivovarov. Ich najpopul\u00e1rnej\u0161\u00edm pivom je Magor a zo \u0161peci\u00e1lov odpor\u00fa\u010dame ochutna\u0165 (a vypi\u0165) skvele odladen\u00fa a nachmelen\u00fa Double IPU.<\/p>",
          "url": "http:\/\/sk.beer-shop.cz\/p\/zlaty-dalmatyn-101",
          "seo_title": null,
          "seo_description": null,
          "seo_url": "zlaty-dalmatyn-101",
          "unit": "ks"
        }
      ],
      "manufacturer": "Beershop",
      "stock": 4,
      "stock_position": null,
      "availability": "Skladem 3-5 ks",
      "availability_type": "InStock",
      "weight": null,
      "shipment_group": null,
      "images": [
        {
          "url": "https:\/\/beershop.s24.cdn-upgates.com\/b\/b65e9c5f1065f0-img-4259.jpg",
          "main_yn": true,
          "list_yn": true,
          "position": 1,
          "titles": []
        },
        {
          "url": "https:\/\/beershop.s24.cdn-upgates.com\/u\/u65e9c5e3cc2ea-img-4346.jpg",
          "main_yn": false,
          "list_yn": false,
          "position": 2,
          "titles": []
        },
        {
          "url": "https:\/\/beershop.s24.cdn-upgates.com\/u\/u65e9c5b010489-img-4345-2.jpg",
          "main_yn": false,
          "list_yn": false,
          "position": 3,
          "titles": []
        }
      ],
      "categories": [],
      "groups": [],
      "prices": [
        {
          "currency": "CZK",
          "language": "cs",
          "pricelists": [
            {
              "name": "V\u00fdchoz\u00ed",
              "price_original": 101,
              "product_discount": null,
              "product_discount_real": 0,
              "price_sale": null,
              "price_with_vat": 101,
              "price_without_vat": 83.47
            }
          ],
          "price_purchase": null,
          "price_common": 0,
          "vat": 21,
          "recycling_fee": null
        },
        {
          "currency": "EUR",
          "language": "en",
          "pricelists": [
            {
              "name": "V\u00fdchoz\u00ed",
              "price_original": 101,
              "product_discount": null,
              "product_discount_real": 0,
              "price_sale": null,
              "price_with_vat": 101,
              "price_without_vat": 101
            }
          ],
          "price_purchase": null,
          "price_common": 0,
          "vat": 0,
          "recycling_fee": null
        },
        {
          "currency": "EUR",
          "language": "sk",
          "pricelists": [
            {
              "name": "V\u00fdchoz\u00ed",
              "price_original": 101,
              "product_discount": null,
              "product_discount_real": 0,
              "price_sale": null,
              "price_with_vat": 101,
              "price_without_vat": 101
            }
          ],
          "price_purchase": null,
          "price_common": 0,
          "vat": 0,
          "recycling_fee": null
        }
      ],
      "variants": [],
      "metas": [
        {
          "key": "categorytext_zbozi_cz",
          "type": "select",
          "value": ""
        },
        {
          "key": "col",
          "type": "input",
          "value": ""
        },
        {
          "key": "cont",
          "type": "input",
          "value": ""
        },
        {
          "key": "custom_zaloha",
          "type": "number",
          "value": "0"
        },
        {
          "key": "productname_zbozi_cz",
          "type": "input",
          "value": ""
        },
        {
          "key": "product_zbozi_cz",
          "type": "input",
          "value": ""
        },
        {
          "key": "redirect_301",
          "type": "textarea",
          "values": {
            "cs": {
              "language": "cs",
              "value": "\/p\/zlaty-dalmatyn-101"
            },
            "en": {
              "language": "en",
              "value": "\/p\/zlaty-dalmatyn-101"
            },
            "sk": {
              "language": "sk",
              "value": "\/p\/zlaty-dalmatyn-101"
            }
          }
        }
      ],
      "creation_time": "2024-03-07T14:10:05+01:00",
      "last_update_time": "2024-03-07T15:25:27+01:00",
      "admin_url": "https:\/\/beershop.admin.s24.upgates.com\/manager\/products\/main\/default\/41"
    }
  ]
}